PooPyLab/__init__.py
PooPyLab/ASMModel/__init__.py
PooPyLab/ASMModel/asm_1.py
PooPyLab/ASMModel/constants.py
PooPyLab/unit_procs/__init__.py
PooPyLab/unit_procs/base.py
PooPyLab/unit_procs/bio.py
PooPyLab/unit_procs/physchem.py
PooPyLab/unit_procs/streams.py
PooPyLab/utils/__init__.py
PooPyLab/utils/datatypes.py
PooPyLab/utils/pfd.py
PooPyLab/utils/run.py
poopylab-0.1.0.20201206.dist-info/LICENSE.txt
poopylab-0.1.0.20201206.dist-info/METADATA
poopylab-0.1.0.20201206.dist-info/WHEEL
poopylab-0.1.0.20201206.dist-info/top_level.txt
poopylab-0.1.0.20201206.dist-info/RECORD
