Metadata-Version: 2.1
Name: poopylab
Version: 0.1.0.20201206
Summary: An open source simulation tool for biological wastewater treatment, by the poop nerds, for the the poop nerds.
Home-page: https://github.com/toogad/PooPyLab_Project
Author: Kai Zhang
Author-email: poopylabproject@gmail.com
License: UNKNOWN
Project-URL: Source, https://github.com/toogad/PooPyLab_Project
Project-URL: Documentation, https://toogad.github.io/brownbook/index.html
Project-URL: Tracker, https://github.com/toogad/PooPyLab_Project/issues
Project-URL: Funding, https://donate.pypi.org
Keywords: Activated Sludge Model ASM Wastewater Simulation
Platform: UNKNOWN
Classifier: Programming Language :: Python :: 3
Classifier: License :: OSI Approved :: GNU General Public License v3 (GPLv3)
Classifier: Operating System :: OS Independent
Requires-Python: >=3
Requires-Dist: scipy
